{"Records":{"Records":{"internalLink":{"count":2,"lastUpdated":1728801472864}}},"Literature":{"Literature":{"currentVault":{"count":1,"lastUpdated":1728802240556}}},"classroom":{"classroom":{"currentFile":{"count":1,"lastUpdated":1728817261257}}},"通过多模态数据分析，为学生了解自身学习行为、教师进行个性化教学以及研究者构建学习评价体系提供数据支持和科学依据。":{"通过多模态数据分析，为学生了解自身学习行为、教师进行个性化教学以及研究者构建学习评价体系提供数据支持和科学依据。":{"currentFile":{"count":1,"lastUpdated":1729476826890}}},"使用OPENPOSE姿态检测网络提取中学生的姿态信息，并通过HPRNN和LFRCNN识别头部姿态和手部周围环境，该方法在确保识别准确性的前提下，可以在同一网络中识别多个学生的行为，有效缓解了样本不足导致的神经网络训练困难问题。":{"使用OPENPOSE姿态检测网络提取中学生的姿态信息，并通过HPRNN和LFRCNN识别头部姿态和手部周围环境，该方法在确保识别准确性的前提下，可以在同一网络中识别多个学生的行为，有效缓解了样本不足导致的神经网络训练困难问题。":{"currentFile":{"count":1,"lastUpdated":1729486726462}}},"1.给位6赋值1":{"1.给位6赋值1":{"currentFile":{"count":1,"lastUpdated":1730085218037}}}}